transcriptic/__init__.py
transcriptic/auth.py
transcriptic/cli.py
transcriptic/commands.py
transcriptic/config.py
transcriptic/english.py
transcriptic/routes.py
transcriptic/util.py
transcriptic/version.py
transcriptic/analysis/__init__.py
transcriptic/analysis/imaging.py
transcriptic/analysis/kinetics.py
transcriptic/analysis/spectrophotometry.py
transcriptic/jupyter/__init__.py
transcriptic/jupyter/common.py
transcriptic/jupyter/container.py
transcriptic/jupyter/dataobject.py
transcriptic/jupyter/dataset.py
transcriptic/jupyter/instruction.py
transcriptic/jupyter/project.py
transcriptic/jupyter/run.py
transcriptic/templates/manifest.json.jinja
transcriptic/templates/protocol.py.jinja
transcriptic/templates/requirements.txt.jinja
transcriptic-9.6.3.dist-info/LICENSE
transcriptic-9.6.3.dist-info/METADATA
transcriptic-9.6.3.dist-info/WHEEL
transcriptic-9.6.3.dist-info/entry_points.txt
transcriptic-9.6.3.dist-info/top_level.txt
transcriptic-9.6.3.dist-info/RECORD
